ae/ae/__init__.py
ae/ae/templates/de_spt_namespace-root_de_otf_de_tpl_README.md
ae_ae-0.3.101.dist-info/licenses/LICENSE.md
ae_ae-0.3.101.dist-info/METADATA
ae_ae-0.3.101.dist-info/WHEEL
ae_ae-0.3.101.dist-info/top_level.txt
ae_ae-0.3.101.dist-info/RECORD
