Metadata-Version: 2.4
Name: ae_ae
Version: 0.3.101
Summary: ae namespace-root: bundling and maintaining templates and documentation of the portions of this namespace.
Home-page: https://gitlab.com/ae-group/ae_ae
Author: AndiEcker
Author-email: aecker2@gmail.com
License: GPL-3.0-or-later
Project-URL: Bug Tracker, https://gitlab.com/ae-group/ae_ae/-/issues
Project-URL: Documentation, https://ae.readthedocs.io/en/latest/_autosummary/ae.ae.html
Project-URL: Repository, https://gitlab.com/ae-group/ae_ae
Project-URL: Source, https://ae.readthedocs.io/en/latest/_modules/ae/ae.html
Keywords: configuration,development,environment,productivity
Classifier: Development Status :: 3 - Alpha
Classifier: Natural Language :: English
Classifier: Operating System :: OS Independent
Classifier: Programming Language :: Python
Classifier: Programming Language :: Python :: 3
Classifier: Programming Language :: Python :: 3.9
Classifier: Topic :: Software Development
Classifier: Typing :: Typed
Requires-Python: >=3.9
License-File: LICENSE.md
Provides-Extra: dev
Requires-Dist: aedev_project_tpls; extra == "dev"
Requires-Dist: aedev_namespace_root_tpls; extra == "dev"
Requires-Dist: ae_base; extra == "dev"
Requires-Dist: ae_deep; extra == "dev"
Requires-Dist: ae_django_utils; extra == "dev"
Requires-Dist: ae_notify; extra == "dev"
Requires-Dist: ae_valid; extra == "dev"
Requires-Dist: ae_files; extra == "dev"
Requires-Dist: ae_paths; extra == "dev"
Requires-Dist: ae_cloud_storage; extra == "dev"
Requires-Dist: ae_oaio_model; extra == "dev"
Requires-Dist: ae_oaio_client; extra == "dev"
Requires-Dist: ae_core; extra == "dev"
Requires-Dist: ae_dynamicod; extra == "dev"
Requires-Dist: ae_i18n; extra == "dev"
Requires-Dist: ae_parse_date; extra == "dev"
Requires-Dist: ae_literal; extra == "dev"
Requires-Dist: ae_updater; extra == "dev"
Requires-Dist: ae_console; extra == "dev"
Requires-Dist: ae_shell; extra == "dev"
Requires-Dist: ae_templates; extra == "dev"
Requires-Dist: ae_dev_ops; extra == "dev"
Requires-Dist: ae_pythonanywhere; extra == "dev"
Requires-Dist: ae_lockname; extra == "dev"
Requires-Dist: ae_progress; extra == "dev"
Requires-Dist: ae_sys_core; extra == "dev"
Requires-Dist: ae_sys_data; extra == "dev"
Requires-Dist: ae_sys_core_sh; extra == "dev"
Requires-Dist: ae_sys_data_sh; extra == "dev"
Requires-Dist: ae_db_core; extra == "dev"
Requires-Dist: ae_db_ora; extra == "dev"
Requires-Dist: ae_db_pg; extra == "dev"
Requires-Dist: ae_transfer_service; extra == "dev"
Requires-Dist: ae_sideloading_server; extra == "dev"
Requires-Dist: ae_gui; extra == "dev"
Requires-Dist: ae_kivy_glsl; extra == "dev"
Requires-Dist: ae_kivy_dyn_chi; extra == "dev"
Requires-Dist: ae_kivy_relief_canvas; extra == "dev"
Requires-Dist: ae_kivy; extra == "dev"
Requires-Dist: ae_kivy_auto_width; extra == "dev"
Requires-Dist: ae_kivy_file_chooser; extra == "dev"
Requires-Dist: ae_kivy_iterable_displayer; extra == "dev"
Requires-Dist: ae_kivy_qr_displayer; extra == "dev"
Requires-Dist: ae_kivy_sideloading; extra == "dev"
Requires-Dist: ae_kivy_user_prefs; extra == "dev"
Requires-Dist: ae_lisz_app_data; extra == "dev"
Requires-Dist: ae_enaml_app; extra == "dev"
Requires-Dist: ae_ae; extra == "dev"
Requires-Dist: sphinx; extra == "dev"
Requires-Dist: sphinx-rtd-theme; extra == "dev"
Requires-Dist: sphinx_autodoc_typehints; extra == "dev"
Requires-Dist: sphinx_paramlinks; extra == "dev"
Requires-Dist: ae_dev_ops; extra == "dev"
Requires-Dist: anybadge; extra == "dev"
Requires-Dist: coverage-badge; extra == "dev"
Requires-Dist: aedev_project_manager; extra == "dev"
Requires-Dist: flake8; extra == "dev"
Requires-Dist: mypy; extra == "dev"
Requires-Dist: pylint; extra == "dev"
Requires-Dist: pytest; extra == "dev"
Requires-Dist: pytest-cov; extra == "dev"
Requires-Dist: pytest-django; extra == "dev"
Requires-Dist: typing; extra == "dev"
Requires-Dist: types-setuptools; extra == "dev"
Provides-Extra: docs
Requires-Dist: sphinx; extra == "docs"
Requires-Dist: sphinx-rtd-theme; extra == "docs"
Requires-Dist: sphinx_autodoc_typehints; extra == "docs"
Requires-Dist: sphinx_paramlinks; extra == "docs"
Requires-Dist: ae_dev_ops; extra == "docs"
Provides-Extra: tests
Requires-Dist: anybadge; extra == "tests"
Requires-Dist: coverage-badge; extra == "tests"
Requires-Dist: aedev_project_manager; extra == "tests"
Requires-Dist: flake8; extra == "tests"
Requires-Dist: mypy; extra == "tests"
Requires-Dist: pylint; extra == "tests"
Requires-Dist: pytest; extra == "tests"
Requires-Dist: pytest-cov; extra == "tests"
Requires-Dist: pytest-django; extra == "tests"
Requires-Dist: typing; extra == "tests"
Requires-Dist: types-setuptools; extra == "tests"
Dynamic: author
Dynamic: author-email
Dynamic: classifier
Dynamic: description
Dynamic: description-content-type
Dynamic: home-page
Dynamic: keywords
Dynamic: license
Dynamic: license-file
Dynamic: project-url
Dynamic: provides-extra
Dynamic: requires-python
Dynamic: summary
